logging_manager/__init__.py
logging_manager/logger.py
logging_manager-0.1.2.dist-info/METADATA
logging_manager-0.1.2.dist-info/WHEEL
logging_manager-0.1.2.dist-info/RECORD
