Metadata-Version: 2.1
Name: logging_manager
Version: 0.1.2
Summary: Sets up logs
Author: giridhar-gitspace
Author-email: gkannappan@suki.ai
Requires-Python: >=3.10,<4
Classifier: Programming Language :: Python :: 3
Classifier: Programming Language :: Python :: 3.10
Classifier: Programming Language :: Python :: 3.11
Classifier: Programming Language :: Python :: 3.12
Classifier: Programming Language :: Python :: 3.13
